eastereig/__init__.py
eastereig/__main__.py
eastereig/_petsc_utils.py
eastereig/adapter.py
eastereig/charpol.py
eastereig/eig.py
eastereig/eigSolvers.py
eastereig/ep.py
eastereig/lda_func.py
eastereig/loci.py
eastereig/op.py
eastereig/options.py
eastereig/utils.py
eastereig/version.py
eastereig/examples/ThreeDoF.py
eastereig/examples/WGadmitance_numpy_mv.py
eastereig/examples/WGadmitance_petsc_mv.py
eastereig/examples/WGadmitance_scipy_mv.py
eastereig/examples/WGimpedance_numpy.py
eastereig/examples/WGimpedance_petsc.py
eastereig/examples/WGimpedance_scipysp.py
eastereig/examples/__init__.py
eastereig/examples/toy_3dof_2params.py
eastereig/fpoly/__init__.py
eastereig/fpoly/_fpoly.py
eastereig/fpoly/_fpolyval_full_py.py
eastereig/fpoly/eastereig.fpoly._fpolyval.cpython-313-x86_64-linux-gnu.so
eastereig/tests/test_charpol.py
eastereig/tests/test_multiindex.py
eastereig-1.4.1.dist-info/LICENSE
eastereig-1.4.1.dist-info/METADATA
eastereig-1.4.1.dist-info/WHEEL
eastereig-1.4.1.dist-info/RECORD
