Metadata-Version: 2.1
Name: eastereig
Version: 1.4.1
Summary: A library to locate exceptional points and to reconstruct eigenvalues loci
Author-Email: "B. Nennig" <benoit.nennig@isae-supmeca.fr>, "M. Ghienne" <martin.ghienne@isae-supmeca.fr>
License:                     GNU GENERAL PUBLIC LICENSE
Classifier: Development Status :: 5 - Production/Stable
Classifier: Topic :: Scientific/Engineering
Classifier: Programming Language :: Python :: 3
Classifier: License :: OSI Approved :: GNU General Public License v3 (GPLv3)
Classifier: Operating System :: OS Independent
Project-URL: homepage, https://github.com/nennigb/EasterEig
Requires-Python: >=3.8
Requires-Dist: numpy
Requires-Dist: scipy
Requires-Dist: sympy>=1.4
Requires-Dist: matplotlib
Requires-Dist: pypolsys
Requires-Dist: tqdm
